{
  "project_info": {
    "project_number": "236690908689",
    "project_id": "petstore-2f1a7",
    "storage_bucket": "petstore-2f1a7.appspot.com"
  },
  "client": [
    {
      "client_info": {
        "mobilesdk_app_id": "1:236690908689:android:2ff7280d1b59937f45f3b0",
        "android_client_info": {
          "package_name": "com.bitknit.pet_store_admin"
        }
      },
      "oauth_client": [],
      "api_key": [
        {
          "current_key": "AIzaSyAWeSEJfwqoGZZb0fM-EFKyyMTQ5t8G8g8"
        }
      ],
      "services": {
        "appinvite_service": {
          "other_platform_oauth_client": []
        }
      }
    },
    {
      "client_info": {
        "mobilesdk_app_id": "1:236690908689:android:efeb3e15fee368df45f3b0",
        "android_client_info": {
          "package_name": "com.example.pet_store_app"
        }
      },
      "oauth_client": [],
      "api_key": [
        {
          "current_key": "AIzaSyAWeSEJfwqoGZZb0fM-EFKyyMTQ5t8G8g8"
        }
      ],
      "services": {
        "appinvite_service": {
          "other_platform_oauth_client": []
        }
      }
    }
  ],
  "configuration_version": "1"
}